IpfsML/__init__.py
IpfsML/store_data_sets.py
Ipfs_apis/__init__.py
Ipfs_apis/ipfs_apis.py
nft_storage/__init__.py
nft_storage/api_client.py
nft_storage/configuration.py
nft_storage/exceptions.py
nft_storage/model_utils.py
nft_storage/rest.py
nft_storage/api/__init__.py
nft_storage/api/nft_storage_api.py
nft_storage/apis/__init__.py
nft_storage/model/__init__.py
nft_storage/model/check_response.py
nft_storage/model/check_response_value.py
nft_storage/model/deal.py
nft_storage/model/delete_response.py
nft_storage/model/error_response.py
nft_storage/model/error_response_error.py
nft_storage/model/files.py
nft_storage/model/forbidden_error_response.py
nft_storage/model/forbidden_error_response_error.py
nft_storage/model/get_response.py
nft_storage/model/links.py
nft_storage/model/links_file.py
nft_storage/model/list_response.py
nft_storage/model/nft.py
nft_storage/model/pin.py
nft_storage/model/pin_status.py
nft_storage/model/unauthorized_error_response.py
nft_storage/model/unauthorized_error_response_error.py
nft_storage/model/upload_response.py
nft_storage/models/__init__.py
IpfsML-1.0.2.dist-info/METADATA
IpfsML-1.0.2.dist-info/WHEEL
IpfsML-1.0.2.dist-info/top_level.txt
IpfsML-1.0.2.dist-info/RECORD
